setup.cfg
setup.py
lambda_cron/__init__.py
lambda_cron/lambda-cron
lambda_cron/requirements.txt
lambda_cron/schema.json
lambda_cron/template.cfn.yml
lambda_cron.egg-info/PKG-INFO
lambda_cron.egg-info/SOURCES.txt
lambda_cron.egg-info/dependency_links.txt
lambda_cron.egg-info/entry_points.txt
lambda_cron.egg-info/requires.txt
lambda_cron.egg-info/top_level.txt
lambda_cron/aws/__init__.py
lambda_cron/aws/main.py
lambda_cron/aws/lib/__init__.py
lambda_cron/aws/lib/cron_checker.py
lambda_cron/aws/lib/task_runner.py
lambda_cron/cli/__init__.py
lambda_cron/cli/cli_config.py
lambda_cron/cli/cli_tool.py
lambda_cron/cli/command/__init__.py
lambda_cron/cli/command/aws_lambda.py
lambda_cron/cli/command/cloudformation.py
lambda_cron/cli/command/command.py
lambda_cron/cli/command/tasks.py